setup.py
iterextra/__init__.py
iterextra.egg-info/PKG-INFO
iterextra.egg-info/SOURCES.txt
iterextra.egg-info/dependency_links.txt
iterextra.egg-info/requires.txt
iterextra.egg-info/top_level.txt