Metadata-Version: 1.1
Name: iterextra
Version: 0.1.1
Summary: An extension to Python standard library itertools
Home-page: https://github.com/adamkal/iterextra
Author: Adam Kaliński
Author-email: UNKNOWN
License: UNKNOWN
Download-URL: https://github.com/code22/iterextra/archive/master.zip
Platform: UNKNOWN
